lzy/__init__.py
lzy/agent_builder.py
lzy/cli.py
lzy/domain.py
lzycli-1.0.0.dist-info/licenses/LICENSE
lzycli-1.0.0.dist-info/METADATA
lzycli-1.0.0.dist-info/WHEEL
lzycli-1.0.0.dist-info/entry_points.txt
lzycli-1.0.0.dist-info/top_level.txt
lzycli-1.0.0.dist-info/RECORD
