Metadata-Version: 2.4
Name: lzycli
Version: 1.0.0
Summary: Translate natural language commands into Linux bash commands.
Author-email: Ricardo Borges <ricardoborges@gmail.com>
License: MIT License
Classifier: Programming Language :: Python :: 3
Classifier: License :: OSI Approved :: MIT License
Classifier: Operating System :: OS Independent
Requires-Python: >=3.7
License-File: LICENSE
Requires-Dist: pydantic>=2.11.4
Requires-Dist: pydantic-ai>=0.1.11
Requires-Dist: python-dotenv
Requires-Dist: rich
Dynamic: license-file
